gemmi-stubs/__init__.pyi
gemmi-stubs/cif.pyi
gemmi_stubs-0.5.8.post2.dist-info/METADATA
gemmi_stubs-0.5.8.post2.dist-info/WHEEL
gemmi_stubs-0.5.8.post2.dist-info/top_level.txt
gemmi_stubs-0.5.8.post2.dist-info/RECORD
