Metadata-Version: 2.1
Name: gemmi-stubs
Version: 0.5.8.post2
Summary: Typing stubs for gemmi
Home-page: https://github.com/eggplants/gemmi-stubs
Author: eggplants
Author-email: w10776e8w@yahoo.co.jp
License: MPL
Classifier: Intended Audience :: Developers
Classifier: Programming Language :: Python
